pylint_sonarjson/__init__.py
pylint_sonarjson/sonarjson_reporter.py
pylint_sonarjson/sonaroptions_checker.py
pylint_sonarjson_catlab-2.0.0.dist-info/LICENSE
pylint_sonarjson_catlab-2.0.0.dist-info/METADATA
pylint_sonarjson_catlab-2.0.0.dist-info/WHEEL
pylint_sonarjson_catlab-2.0.0.dist-info/top_level.txt
pylint_sonarjson_catlab-2.0.0.dist-info/RECORD
