Metadata-Version: 2.1
Name: pylint-sonarjson-catlab
Version: 2.0.0
Summary: A PyLint plugin that can output to SonarQube-importable JSON
Home-page: https://github.com/cnescatlab/pylint-sonarjson-catlab 
Author: Teake Nutma, Topin2001
Classifier: Programming Language :: Python :: 3
Classifier: License :: OSI Approved :: GNU Lesser General Public License v3 (LGPLv3)
Classifier: Operating System :: OS Independent
Requires-Python: >=3.7
License-File: LICENSE
Requires-Dist: pylint-plugin-utils >=0.7
Requires-Dist: pylint <4,>=3.0.0
